{
  "id": "1069605",
  "name": "云报账",
  "font_family": "iconfont",
  "css_prefix_text": "icon",
  "description": "SAAS",
  "glyphs": [
    {
      "icon_id": "8858996",
      "name": "50_我的已结",
      "font_class": "_wodeyijie",
      "unicode": "e638",
      "unicode_decimal": 58936
    },
    {
      "icon_id": "8858997",
      "name": "50_ 我的行程",
      "font_class": "_wodehangcheng",
      "unicode": "e639",
      "unicode_decimal": 58937
    },
    {
      "icon_id": "8858998",
      "name": "50_我的已办",
      "font_class": "_wodeyiban",
      "unicode": "e63a",
      "unicode_decimal": 58938
    },
    {
      "icon_id": "8858999",
      "name": "50_我的待办",
      "font_class": "_wodedaiban",
      "unicode": "e63b",
      "unicode_decimal": 58939
    },
    {
      "icon_id": "8859003",
      "name": "16_箭头减",
      "font_class": "_jiantoujian",
      "unicode": "e63c",
      "unicode_decimal": 58940
    },
    {
      "icon_id": "8859004",
      "name": "16_箭头增",
      "font_class": "_jiantouzeng",
      "unicode": "e63d",
      "unicode_decimal": 58941
    },
    {
      "icon_id": "8859010",
      "name": "16_top下拉下",
      "font_class": "_topxialaxia",
      "unicode": "e63e",
      "unicode_decimal": 58942
    },
    {
      "icon_id": "8859011",
      "name": "16_top搜索",
      "font_class": "_topsousuo",
      "unicode": "e63f",
      "unicode_decimal": 58943
    },
    {
      "icon_id": "8859012",
      "name": "18_top消息",
      "font_class": "_topxiaoxi",
      "unicode": "e640",
      "unicode_decimal": 58944
    },
    {
      "icon_id": "8859013",
      "name": "18_top日期",
      "font_class": "_topriqi",
      "unicode": "e641",
      "unicode_decimal": 58945
    },
    {
      "icon_id": "8859014",
      "name": "16_top下拉上",
      "font_class": "_topxialashang",
      "unicode": "e642",
      "unicode_decimal": 58946
    },
    {
      "icon_id": "8859015",
      "name": "18_top首页",
      "font_class": "_topshouye",
      "unicode": "e643",
      "unicode_decimal": 58947
    },
    {
      "icon_id": "8859041",
      "name": "12_CD箭头",
      "font_class": "_CDjiantou",
      "unicode": "e644",
      "unicode_decimal": 58948
    },
    {
      "icon_id": "8859042",
      "name": "12_CD箭头H",
      "font_class": "_CDjiantouH",
      "unicode": "e645",
      "unicode_decimal": 58949
    },
    {
      "icon_id": "8859043",
      "name": "16_CD收起",
      "font_class": "_CDshouqi",
      "unicode": "e646",
      "unicode_decimal": 58950
    },
    {
      "icon_id": "8859044",
      "name": "16_CD商旅协同",
      "font_class": "_CDshanglvxietong",
      "unicode": "e647",
      "unicode_decimal": 58951
    },
    {
      "icon_id": "8859045",
      "name": "16_CD统计查询",
      "font_class": "_CDtongjichaxun",
      "unicode": "e648",
      "unicode_decimal": 58952
    },
    {
      "icon_id": "8859046",
      "name": "16_CD展开",
      "font_class": "_CDzhankai",
      "unicode": "e649",
      "unicode_decimal": 58953
    },
    {
      "icon_id": "8859047",
      "name": "16_CD预算管理",
      "font_class": "_CDyusuanguanli",
      "unicode": "e64a",
      "unicode_decimal": 58954
    },
    {
      "icon_id": "8859048",
      "name": "16_CD系统配置",
      "font_class": "_CDxitongpeizhi",
      "unicode": "e64b",
      "unicode_decimal": 58955
    },
    {
      "icon_id": "8859049",
      "name": "16_CD日常报销",
      "font_class": "_CDrichangbaoxiao",
      "unicode": "e64c",
      "unicode_decimal": 58956
    },
    {
      "icon_id": "8859050",
      "name": "16_CD日常业务",
      "font_class": "_CDrichangyewu",
      "unicode": "e64d",
      "unicode_decimal": 58957
    },
    {
      "icon_id": "8859051",
      "name": "16_CD票据采集",
      "font_class": "_CDpiaojucaiji",
      "unicode": "e64e",
      "unicode_decimal": 58958
    },
    {
      "icon_id": "8859052",
      "name": "16_CD枚举字典",
      "font_class": "_CDmeijuzidian",
      "unicode": "e64f",
      "unicode_decimal": 58959
    },
    {
      "icon_id": "8859053",
      "name": "16_CD系统设置",
      "font_class": "_CDxitongshezhi",
      "unicode": "e650",
      "unicode_decimal": 58960
    },
    {
      "icon_id": "8859055",
      "name": "16_CD系统管理",
      "font_class": "_CDxitongguanli",
      "unicode": "e651",
      "unicode_decimal": 58961
    },
    {
      "icon_id": "8859056",
      "name": "16_CD基础数据",
      "font_class": "_CDjichushuju",
      "unicode": "e652",
      "unicode_decimal": 58962
    },
    {
      "icon_id": "8859057",
      "name": "16_CD个人中心",
      "font_class": "_CDgerenzhongxin",
      "unicode": "e653",
      "unicode_decimal": 58963
    },
    {
      "icon_id": "8859066",
      "name": "12_YQ首页",
      "font_class": "_YQshouye",
      "unicode": "e654",
      "unicode_decimal": 58964
    },
    {
      "icon_id": "8859067",
      "name": "12_YQ关闭",
      "font_class": "_YQguanbi",
      "unicode": "e655",
      "unicode_decimal": 58965
    },
    {
      "icon_id": "8859068",
      "name": "16_YQ关闭更多",
      "font_class": "_YQguanbigengduo",
      "unicode": "e656",
      "unicode_decimal": 58966
    },
    {
      "icon_id": "8859069",
      "name": "16_YQ全部关闭",
      "font_class": "_YQquanbuguanbi",
      "unicode": "e657",
      "unicode_decimal": 58967
    },
    {
      "icon_id": "8859103",
      "name": "14_输入框下拉下",
      "font_class": "_shurukuangxialaxia",
      "unicode": "e658",
      "unicode_decimal": 58968
    },
    {
      "icon_id": "8859104",
      "name": "14_输入框下拉上",
      "font_class": "_shurukuangxialashang",
      "unicode": "e659",
      "unicode_decimal": 58969
    },
    {
      "icon_id": "8860247",
      "name": "14_输入框关闭",
      "font_class": "_shurukuangguanbi",
      "unicode": "e65a",
      "unicode_decimal": 58970
    },
    {
      "icon_id": "8860248",
      "name": "14_输入框日期",
      "font_class": "_shurukuangriqi",
      "unicode": "e65b",
      "unicode_decimal": 58971
    },
    {
      "icon_id": "8860250",
      "name": "16_输入框搜索用户管理",
      "font_class": "_shurukuangsousuoyonghuguanli",
      "unicode": "e65d",
      "unicode_decimal": 58973
    },
    {
      "icon_id": "8860251",
      "name": "16_输入框金额",
      "font_class": "_shurukuangjine",
      "unicode": "e65e",
      "unicode_decimal": 58974
    },
    {
      "icon_id": "8860252",
      "name": "16_输入框删除",
      "font_class": "_shurukuangshanchu",
      "unicode": "e65f",
      "unicode_decimal": 58975
    },
    {
      "icon_id": "8860254",
      "name": "16_输入框搜索",
      "font_class": "_shurukuangsousuo",
      "unicode": "e661",
      "unicode_decimal": 58977
    },
    {
      "icon_id": "8860255",
      "name": "14_输入框删除",
      "font_class": "_shurukuangshanchu1",
      "unicode": "e662",
      "unicode_decimal": 58978
    },
    {
      "icon_id": "8860426",
      "name": "16_g修改密码",
      "font_class": "_gxiugaimima",
      "unicode": "e65c",
      "unicode_decimal": 58972
    },
    {
      "icon_id": "8860427",
      "name": "16_g个人信息",
      "font_class": "_ggerenxinxi",
      "unicode": "e660",
      "unicode_decimal": 58976
    },
    {
      "icon_id": "8860428",
      "name": "16_g注销",
      "font_class": "_gzhuxiao",
      "unicode": "e663",
      "unicode_decimal": 58979
    },
    {
      "icon_id": "8860436",
      "name": "14_sx-查询下拉箭头-收起",
      "font_class": "_sx-chaxunxialajiantou-shouqi",
      "unicode": "e664",
      "unicode_decimal": 58980
    },
    {
      "icon_id": "8860438",
      "name": "14_sx-查询下拉箭头-展开",
      "font_class": "_sx-chaxunxialajiantou-zhankai",
      "unicode": "e665",
      "unicode_decimal": 58981
    },
    {
      "icon_id": "8860449",
      "name": "14_sx-筛选",
      "font_class": "_sx-shaixuan",
      "unicode": "e666",
      "unicode_decimal": 58982
    },
    {
      "icon_id": "8860450",
      "name": "14_sx-其他下拉箭头-展开",
      "font_class": "_sx-qitaxialajiantou-zhankai",
      "unicode": "e667",
      "unicode_decimal": 58983
    },
    {
      "icon_id": "8860451",
      "name": "14_sx-其他下拉箭头-收起",
      "font_class": "_sx-qitaxialajiantou-shouqi",
      "unicode": "e668",
      "unicode_decimal": 58984
    },
    {
      "icon_id": "8860464",
      "name": "16_yq页签更多-收起",
      "font_class": "_yqyeqiangengduo-shouqi",
      "unicode": "e669",
      "unicode_decimal": 58985
    },
    {
      "icon_id": "8860465",
      "name": "16_yq页签更多-展开",
      "font_class": "_yqyeqiangengduo-zhankai",
      "unicode": "e66a",
      "unicode_decimal": 58986
    },
    {
      "icon_id": "8860467",
      "name": "20_gjl工具栏更多-展开",
      "font_class": "_gjlgongjulangengduo-zhankai",
      "unicode": "e66b",
      "unicode_decimal": 58987
    },
    {
      "icon_id": "8860468",
      "name": "20_gjl工具栏更多-收起",
      "font_class": "_gjlgongjulangengduo-shouqi",
      "unicode": "e66c",
      "unicode_decimal": 58988
    },
    {
      "icon_id": "8860473",
      "name": "16_fj-图片",
      "font_class": "_fj-tupian",
      "unicode": "e66d",
      "unicode_decimal": 58989
    },
    {
      "icon_id": "8860474",
      "name": "16_fj-doc",
      "font_class": "_fj-doc",
      "unicode": "e66e",
      "unicode_decimal": 58990
    },
    {
      "icon_id": "8860475",
      "name": "16_fj-pdf",
      "font_class": "_fj-pdf",
      "unicode": "e66f",
      "unicode_decimal": 58991
    },
    {
      "icon_id": "8860495",
      "name": "16_fj-成功",
      "font_class": "_fj-chenggong",
      "unicode": "e670",
      "unicode_decimal": 58992
    },
    {
      "icon_id": "8860500",
      "name": "14_ewm制单中图标    ",
      "font_class": "_ewmzhidanzhongtubiao",
      "unicode": "e671",
      "unicode_decimal": 58993
    },
    {
      "icon_id": "8860504",
      "name": "16_ewm审核要点-黄",
      "font_class": "_ewmshenheyaodian-huang",
      "unicode": "e672",
      "unicode_decimal": 58994
    },
    {
      "icon_id": "8860505",
      "name": "16_ewm审核要点-lv",
      "font_class": "_ewmshenheyaodian-lv",
      "unicode": "e673",
      "unicode_decimal": 58995
    },
    {
      "icon_id": "8860506",
      "name": "16_ewm审核要点-红",
      "font_class": "_ewmshenheyaodian-hong",
      "unicode": "e674",
      "unicode_decimal": 58996
    },
    {
      "icon_id": "8860538",
      "name": "14_tk关闭",
      "font_class": "_tkguanbi",
      "unicode": "e675",
      "unicode_decimal": 58997
    },
    {
      "icon_id": "8860539",
      "name": "14_tk箭头右-选中",
      "font_class": "_tkjiantouyou-xuanzhong",
      "unicode": "e676",
      "unicode_decimal": 58998
    },
    {
      "icon_id": "8860540",
      "name": "14_tk箭头右",
      "font_class": "_tkjiantouyou",
      "unicode": "e677",
      "unicode_decimal": 58999
    },
    {
      "icon_id": "8860578",
      "name": "12_shu箭头右-选中状态",
      "font_class": "_shujiantouyou-xuanzhongzhuangtai",
      "unicode": "e678",
      "unicode_decimal": 59000
    },
    {
      "icon_id": "8860579",
      "name": "12_箭头单据展开",
      "font_class": "_jiantoudanjuzhankai",
      "unicode": "e679",
      "unicode_decimal": 59001
    },
    {
      "icon_id": "8860580",
      "name": "12_shu箭头下",
      "font_class": "_shujiantouxia",
      "unicode": "e67a",
      "unicode_decimal": 59002
    },
    {
      "icon_id": "8860581",
      "name": "12_箭头单据收起",
      "font_class": "_jiantoudanjushouqi",
      "unicode": "e67b",
      "unicode_decimal": 59003
    },
    {
      "icon_id": "8860582",
      "name": "12_shu箭头右",
      "font_class": "_shujiantouyou",
      "unicode": "e67c",
      "unicode_decimal": 59004
    },
    {
      "icon_id": "8860603",
      "name": "26_刷新",
      "font_class": "_shuaxin",
      "unicode": "e67d",
      "unicode_decimal": 59005
    },
    {
      "icon_id": "8861061",
      "name": "16_T警告提示",
      "font_class": "_Tjinggaotishi",
      "unicode": "e680",
      "unicode_decimal": 59008
    },
    {
      "icon_id": "8861062",
      "name": "16_T成功提示",
      "font_class": "_Tchenggongtishi",
      "unicode": "e681",
      "unicode_decimal": 59009
    },
    {
      "icon_id": "8861063",
      "name": "16_T疑问提示",
      "font_class": "_Tyiwentishi",
      "unicode": "e682",
      "unicode_decimal": 59010
    },
    {
      "icon_id": "8861064",
      "name": "16_T消息提示",
      "font_class": "_Txiaoxitishi",
      "unicode": "e683",
      "unicode_decimal": 59011
    },
    {
      "icon_id": "8861065",
      "name": "16_T错误提示",
      "font_class": "_Tcuowutishi",
      "unicode": "e684",
      "unicode_decimal": 59012
    },
    {
      "icon_id": "8861068",
      "name": "24_疑问提示",
      "font_class": "_yiwentishi",
      "unicode": "e685",
      "unicode_decimal": 59013
    },
    {
      "icon_id": "8861069",
      "name": "24_警告提示",
      "font_class": "_jinggaotishi",
      "unicode": "e686",
      "unicode_decimal": 59014
    },
    {
      "icon_id": "8861070",
      "name": "24_ 成功提示",
      "font_class": "_chenggongtishi",
      "unicode": "e687",
      "unicode_decimal": 59015
    },
    {
      "icon_id": "8861071",
      "name": "24_警告提示l",
      "font_class": "_jinggaotishil",
      "unicode": "e688",
      "unicode_decimal": 59016
    },
    {
      "icon_id": "8861072",
      "name": "24_错误提示",
      "font_class": "_cuowutishi",
      "unicode": "e689",
      "unicode_decimal": 59017
    },
    {
      "icon_id": "8861074",
      "name": "24_k警告提示l",
      "font_class": "_kjinggaotishil",
      "unicode": "e68a",
      "unicode_decimal": 59018
    },
    {
      "icon_id": "8861075",
      "name": "24_k疑问提示",
      "font_class": "_kyiwentishi",
      "unicode": "e68b",
      "unicode_decimal": 59019
    },
    {
      "icon_id": "8861076",
      "name": "24_k错误提示",
      "font_class": "_kcuowutishi",
      "unicode": "e68c",
      "unicode_decimal": 59020
    },
    {
      "icon_id": "8861077",
      "name": "24_k警告提示",
      "font_class": "_kjinggaotishi",
      "unicode": "e68d",
      "unicode_decimal": 59021
    },
    {
      "icon_id": "8861078",
      "name": "24_ 成功提示k",
      "font_class": "_chenggongtishik",
      "unicode": "e68e",
      "unicode_decimal": 59022
    },
    {
      "icon_id": "8861079",
      "name": "24_完成对勾",
      "font_class": "_wanchengduigou",
      "unicode": "e68f",
      "unicode_decimal": 59023
    },
    {
      "icon_id": "8861080",
      "name": "24_错误",
      "font_class": "_cuowu",
      "unicode": "e690",
      "unicode_decimal": 59024
    },
    {
      "icon_id": "8861094",
      "name": "36_k疑问提示",
      "font_class": "_kyiwentishi1",
      "unicode": "e691",
      "unicode_decimal": 59025
    },
    {
      "icon_id": "8861095",
      "name": "36_ k成功提示",
      "font_class": "_kchenggongtishi",
      "unicode": "e692",
      "unicode_decimal": 59026
    },
    {
      "icon_id": "8861096",
      "name": "36_k错误提示",
      "font_class": "_kcuowutishi1",
      "unicode": "e693",
      "unicode_decimal": 59027
    },
    {
      "icon_id": "8861097",
      "name": "36_k警告提示l",
      "font_class": "_kjinggaotishil1",
      "unicode": "e694",
      "unicode_decimal": 59028
    },
    {
      "icon_id": "8861098",
      "name": "36_k警告提示",
      "font_class": "_kjinggaotishi1",
      "unicode": "e695",
      "unicode_decimal": 59029
    },
    {
      "icon_id": "8861117",
      "name": "12_减行",
      "font_class": "_jianhang",
      "unicode": "e67e",
      "unicode_decimal": 59006
    },
    {
      "icon_id": "8861118",
      "name": "12_增行",
      "font_class": "_zenghang",
      "unicode": "e67f",
      "unicode_decimal": 59007
    },
    {
      "icon_id": "8861120",
      "name": "16_流程当前",
      "font_class": "_liuchengdangqian",
      "unicode": "e696",
      "unicode_decimal": 59030
    },
    {
      "icon_id": "8861121",
      "name": "16_流程",
      "font_class": "_liucheng",
      "unicode": "e697",
      "unicode_decimal": 59031
    },
    {
      "icon_id": "9370410",
      "name": "14_输入框更多",
      "font_class": "_shurukuanggengduo",
      "unicode": "e6c0",
      "unicode_decimal": 59072
    },
    {
      "icon_id": "9375237",
      "name": "14_树-文件夹",
      "font_class": "_shu-wenjianjia",
      "unicode": "e698",
      "unicode_decimal": 59032
    },
    {
      "icon_id": "9375457",
      "name": "14_弹出更多",
      "font_class": "_danchugengduo",
      "unicode": "e69a",
      "unicode_decimal": 59034
    },
    {
      "icon_id": "9375850",
      "name": "14_树-表",
      "font_class": "_shu-biao",
      "unicode": "e699",
      "unicode_decimal": 59033
    },
    {
      "icon_id": "9546701",
      "name": "16_流程在线沟通",
      "font_class": "_liuchengzaixiangoutong",
      "unicode": "e69b",
      "unicode_decimal": 59035
    },
    {
      "icon_id": "9594751",
      "name": "14_ewm驳回可提交",
      "font_class": "_ewmbohuiketijiao",
      "unicode": "e69c",
      "unicode_decimal": 59036
    },
    {
      "icon_id": "9594752",
      "name": "14_ewm审批通过",
      "font_class": "_ewmshenpitongguo",
      "unicode": "e69d",
      "unicode_decimal": 59037
    },
    {
      "icon_id": "9594753",
      "name": "14_ewm已确认-暂不同",
      "font_class": "_ewmyiqueren-zanbutong",
      "unicode": "e69e",
      "unicode_decimal": 59038
    },
    {
      "icon_id": "9594754",
      "name": "14_ewm审批中",
      "font_class": "_ewmshenpizhong",
      "unicode": "e69f",
      "unicode_decimal": 59039
    },
    {
      "icon_id": "9594755",
      "name": "14_ewm驳回不可提交",
      "font_class": "_ewmbohuibuketijiao",
      "unicode": "e6a0",
      "unicode_decimal": 59040
    },
    {
      "icon_id": "9594756",
      "name": "14_ewm已废止",
      "font_class": "_ewmyifeizhi",
      "unicode": "e6a1",
      "unicode_decimal": 59041
    },
    {
      "icon_id": "9594757",
      "name": "14_ewm已提交",
      "font_class": "_ewmyitijiao",
      "unicode": "e6a2",
      "unicode_decimal": 59042
    },
    {
      "icon_id": "9703366",
      "name": "14_公式编辑",
      "font_class": "_gongshibianji",
      "unicode": "e6a3",
      "unicode_decimal": 59043
    },
    {
      "icon_id": "10002406",
      "name": "20_流程-会签-完成",
      "font_class": "_liucheng-huiqian-wancheng",
      "unicode": "e6a5",
      "unicode_decimal": 59045
    },
    {
      "icon_id": "10002408",
      "name": "20_流程-会签-驳回",
      "font_class": "_liucheng-huiqian-bohui",
      "unicode": "e6a7",
      "unicode_decimal": 59047
    },
    {
      "icon_id": "10002409",
      "name": "20_流程-会签-当前",
      "font_class": "_liucheng-huiqian-dangqian",
      "unicode": "e6a8",
      "unicode_decimal": 59048
    },
    {
      "icon_id": "10002440",
      "name": "12_流程-会签-待审批",
      "font_class": "_liucheng-huiqian-daishenpi",
      "unicode": "e6a4",
      "unicode_decimal": 59044
    },
    {
      "icon_id": "10002441",
      "name": "12_流程-会签-已审批",
      "font_class": "_liucheng-huiqian-yishenpi",
      "unicode": "e6a6",
      "unicode_decimal": 59046
    },
    {
      "icon_id": "10036797",
      "name": "24_gs大纲",
      "font_class": "_gsdagang",
      "unicode": "e6ab",
      "unicode_decimal": 59051
    },
    {
      "icon_id": "10036842",
      "name": "24_gs大于等于",
      "font_class": "_gsdayudengyu",
      "unicode": "e6ac",
      "unicode_decimal": 59052
    },
    {
      "icon_id": "10036843",
      "name": "24_gs小于",
      "font_class": "_gsxiaoyu",
      "unicode": "e6ad",
      "unicode_decimal": 59053
    },
    {
      "icon_id": "10036844",
      "name": "24_gs大于",
      "font_class": "_gsdayu",
      "unicode": "e6ae",
      "unicode_decimal": 59054
    },
    {
      "icon_id": "10036845",
      "name": "24_gs等于",
      "font_class": "_gsdengyu",
      "unicode": "e6af",
      "unicode_decimal": 59055
    },
    {
      "icon_id": "10036846",
      "name": "24_gs加",
      "font_class": "_gsjia",
      "unicode": "e6b0",
      "unicode_decimal": 59056
    },
    {
      "icon_id": "10036847",
      "name": "24_gs小于等于",
      "font_class": "_gsxiaoyudengyu",
      "unicode": "e6b1",
      "unicode_decimal": 59057
    },
    {
      "icon_id": "10036848",
      "name": "24_gs除",
      "font_class": "_gschu",
      "unicode": "e6b2",
      "unicode_decimal": 59058
    },
    {
      "icon_id": "10036849",
      "name": "24_gs乘",
      "font_class": "_gscheng",
      "unicode": "e6b3",
      "unicode_decimal": 59059
    },
    {
      "icon_id": "10036850",
      "name": "24_gs减",
      "font_class": "_gsjian",
      "unicode": "e6b4",
      "unicode_decimal": 59060
    },
    {
      "icon_id": "10039207",
      "name": "14_排序鼠标划上",
      "font_class": "_paixushubiaohuashang",
      "unicode": "e6a9",
      "unicode_decimal": 59049
    },
    {
      "icon_id": "10039208",
      "name": "14_排序",
      "font_class": "_paixu",
      "unicode": "e6aa",
      "unicode_decimal": 59050
    },
    {
      "icon_id": "10181964",
      "name": "28_gzl开始",
      "font_class": "_gzlkaishi",
      "unicode": "e6c3",
      "unicode_decimal": 59075
    },
    {
      "icon_id": "10181973",
      "name": "28_gzl任务",
      "font_class": "_gzlrenwu",
      "unicode": "e6c4",
      "unicode_decimal": 59076
    },
    {
      "icon_id": "10181974",
      "name": "28_gzl中间捕捉",
      "font_class": "_gzlzhongjianbuzhuo",
      "unicode": "e6c5",
      "unicode_decimal": 59077
    },
    {
      "icon_id": "10181975",
      "name": "28_gzl中间抛出",
      "font_class": "_gzlzhongjianpaochu",
      "unicode": "e6c6",
      "unicode_decimal": 59078
    },
    {
      "icon_id": "10181977",
      "name": "28_gzl结束",
      "font_class": "_gzljieshu",
      "unicode": "e6c7",
      "unicode_decimal": 59079
    },
    {
      "icon_id": "10181978",
      "name": "28_gzl泳道",
      "font_class": "_gzlyongdao",
      "unicode": "e6c8",
      "unicode_decimal": 59080
    },
    {
      "icon_id": "10181981",
      "name": "28_gzl网关",
      "font_class": "_gzlwangguan",
      "unicode": "e6c9",
      "unicode_decimal": 59081
    },
    {
      "icon_id": "10181986",
      "name": "28_gzl开始点击",
      "font_class": "_gzlkaishidianji",
      "unicode": "e6ca",
      "unicode_decimal": 59082
    },
    {
      "icon_id": "10181987",
      "name": "28_gzl任务点击",
      "font_class": "_gzlrenwudianji",
      "unicode": "e6cb",
      "unicode_decimal": 59083
    },
    {
      "icon_id": "10181996",
      "name": "28_gzl中间捕捉点击",
      "font_class": "_gzlzhongjianbuzhuodianji",
      "unicode": "e6cc",
      "unicode_decimal": 59084
    },
    {
      "icon_id": "10181997",
      "name": "28_gzl中间抛出点击",
      "font_class": "_gzlzhongjianpaochudianji",
      "unicode": "e6cd",
      "unicode_decimal": 59085
    },
    {
      "icon_id": "10181998",
      "name": "28_gzl结束点击",
      "font_class": "_gzljieshudianji",
      "unicode": "e6ce",
      "unicode_decimal": 59086
    },
    {
      "icon_id": "10182004",
      "name": "28_gzl泳道点击",
      "font_class": "_gzlyongdaodianji",
      "unicode": "e6cf",
      "unicode_decimal": 59087
    },
    {
      "icon_id": "10182011",
      "name": "28_gzl网关点击",
      "font_class": "_gzlwangguandianji",
      "unicode": "e6d0",
      "unicode_decimal": 59088
    },
    {
      "icon_id": "10182029",
      "name": "16_gzl任务",
      "font_class": "_gzlrenwu1",
      "unicode": "e6d1",
      "unicode_decimal": 59089
    },
    {
      "icon_id": "10182031",
      "name": "16_gzl结束",
      "font_class": "_gzljieshu1",
      "unicode": "e6d2",
      "unicode_decimal": 59090
    },
    {
      "icon_id": "10183088",
      "name": "16_gzl连线",
      "font_class": "_gzllianxian",
      "unicode": "e6df",
      "unicode_decimal": 59103
    },
    {
      "icon_id": "10183090",
      "name": "16_gzl网关",
      "font_class": "_gzlwangguan1",
      "unicode": "e6e0",
      "unicode_decimal": 59104
    },
    {
      "icon_id": "10183107",
      "name": "4_gzl圆",
      "font_class": "_gzlyuan",
      "unicode": "e6e5",
      "unicode_decimal": 59109
    },
    {
      "icon_id": "10183109",
      "name": "8_gzl箭头",
      "font_class": "_gzljiantou",
      "unicode": "e6e6",
      "unicode_decimal": 59110
    },
    {
      "icon_id": "10183110",
      "name": "8_gzl圆",
      "font_class": "_gzlyuan1",
      "unicode": "e6e7",
      "unicode_decimal": 59111
    },
    {
      "icon_id": "10345349",
      "name": "34_gzl开始",
      "font_class": "_gzlkaishi1",
      "unicode": "e6e8",
      "unicode_decimal": 59112
    },
    {
      "icon_id": "10345353",
      "name": "34_gzl任务",
      "font_class": "_gzlrenwu2",
      "unicode": "e6e9",
      "unicode_decimal": 59113
    },
    {
      "icon_id": "10345354",
      "name": "34_gzl网关",
      "font_class": "_gzlwangguan2",
      "unicode": "e6ea",
      "unicode_decimal": 59114
    },
    {
      "icon_id": "10345356",
      "name": "34_gzl结束",
      "font_class": "_gzljieshu2",
      "unicode": "e6eb",
      "unicode_decimal": 59115
    },
    {
      "icon_id": "10708935",
      "name": "14_锁-选定",
      "font_class": "_suo-xuanding",
      "unicode": "e6ec",
      "unicode_decimal": 59116
    },
    {
      "icon_id": "10708936",
      "name": "14_锁-鼠标划上",
      "font_class": "_suo-shubiaohuashang",
      "unicode": "e6ed",
      "unicode_decimal": 59117
    },
    {
      "icon_id": "10708937",
      "name": "14_锁-正常",
      "font_class": "_suo-zhengchang",
      "unicode": "e6ee",
      "unicode_decimal": 59118
    },
    {
      "icon_id": "10708943",
      "name": "14_s修改z",
      "font_class": "_sxiugaiz",
      "unicode": "e6ef",
      "unicode_decimal": 59119
    },
    {
      "icon_id": "10708944",
      "name": "14_s删除z",
      "font_class": "_sshanchuz",
      "unicode": "e6f0",
      "unicode_decimal": 59120
    },
    {
      "icon_id": "10708955",
      "name": "14_s删除d",
      "font_class": "_sshanchud",
      "unicode": "e6f1",
      "unicode_decimal": 59121
    },
    {
      "icon_id": "10708956",
      "name": "14_s修改d",
      "font_class": "_sxiugaid",
      "unicode": "e6f2",
      "unicode_decimal": 59122
    },
    {
      "icon_id": "10708970",
      "name": "14_s修改表z",
      "font_class": "_sxiugaibiaoz",
      "unicode": "e6f3",
      "unicode_decimal": 59123
    },
    {
      "icon_id": "10708971",
      "name": "14_s新增表z",
      "font_class": "_sxinzengbiaoz",
      "unicode": "e6f4",
      "unicode_decimal": 59124
    },
    {
      "icon_id": "10708972",
      "name": "14_s删除表z",
      "font_class": "_sshanchubiaoz",
      "unicode": "e6f5",
      "unicode_decimal": 59125
    },
    {
      "icon_id": "10708986",
      "name": "14_s新增表d",
      "font_class": "_sxinzengbiaod",
      "unicode": "e6f6",
      "unicode_decimal": 59126
    },
    {
      "icon_id": "10708987",
      "name": "14_s删除表d",
      "font_class": "_sshanchubiaod",
      "unicode": "e6f7",
      "unicode_decimal": 59127
    },
    {
      "icon_id": "10708988",
      "name": "14_s修改表d",
      "font_class": "_sxiugaibiaod",
      "unicode": "e6f8",
      "unicode_decimal": 59128
    },
    {
      "icon_id": "10818387",
      "name": "8_添加加号",
      "font_class": "_tianjiajiahao",
      "unicode": "e6d9",
      "unicode_decimal": 59097
    },
    {
      "icon_id": "11129601",
      "name": "14_对号",
      "font_class": "_duihao",
      "unicode": "e6f9",
      "unicode_decimal": 59129
    },
    {
      "icon_id": "11343150",
      "name": "16_CD应收应付",
      "font_class": "_CDyingshouyingfu",
      "unicode": "e6fa",
      "unicode_decimal": 59130
    },
    {
      "icon_id": "12004764",
      "name": "16_流程当前状态",
      "font_class": "_liuchengdangqianzhuangtai",
      "unicode": "e6fb",
      "unicode_decimal": 59131
    },
    {
      "icon_id": "12004850",
      "name": "26_流程审批完成-灰",
      "font_class": "_liuchengshenpiwancheng-hui",
      "unicode": "e6fc",
      "unicode_decimal": 59132
    },
    {
      "icon_id": "12004851",
      "name": "26_流程审批完成",
      "font_class": "_liuchengshenpiwancheng",
      "unicode": "e6fd",
      "unicode_decimal": 59133
    },
    {
      "icon_id": "12641326",
      "name": "14_sx-快捷",
      "font_class": "_sx-kuaijie",
      "unicode": "e6fe",
      "unicode_decimal": 59134
    }
  ]
}
